retrie/__init__.py
retrie/_repo_version.py
retrie/retrie.py
retrie/trie.py
retrie-0.3.1.dist-info/LICENSE
retrie-0.3.1.dist-info/METADATA
retrie-0.3.1.dist-info/WHEEL
retrie-0.3.1.dist-info/top_level.txt
retrie-0.3.1.dist-info/RECORD
