Metadata-Version: 2.1
Name: retrie
Version: 0.3.1
Summary: Efficient Trie-based regex unions for blacklist/whitelist filtering and one-pass mapping-based string replacing
Home-page: https://github.com/ddelange/retrie
Author: ddelange
Author-email: ddelange@delange.dev
License: MIT
Keywords: pure-Python regex trie regex-trie blacklist whitelist re search replace
Classifier: Development Status :: 5 - Production/Stable
Classifier: Intended Audience :: Developers
Classifier: License :: OSI Approved :: MIT License
Classifier: Operating System :: OS Independent
Classifier: Programming Language :: Python
Classifier: Programming Language :: Python :: 2
Classifier: Programming Language :: Python :: 2.7
Classifier: Programming Language :: Python :: 3
Classifier: Programming Language :: Python :: 3.5
Classifier: Programming Language :: Python :: 3.6
Classifier: Programming Language :: Python :: 3.7
Classifier: Programming Language :: Python :: 3.8
Classifier: Programming Language :: Python :: 3.9
Classifier: Programming Language :: Python :: 3.10
Classifier: Programming Language :: Python :: 3.11
Classifier: Programming Language :: Python :: 3.12
Classifier: Topic :: Software Development :: Libraries :: Python Modules
Classifier: Topic :: Utilities
Requires-Python: >=2.7, !=3.0.*, !=3.1.*, !=3.2.*, !=3.3.*, !=3.4.*
License-File: LICENSE
Requires-Dist: typing ; python_version < "3.5"
Requires-Dist: cached-property ; python_version < "3.8"
